cpp_linter/__init__.py
cpp_linter/_version.py
cpp_linter/cli.py
cpp_linter/loggers.py
cpp_linter/clang_tools/__init__.py
cpp_linter/clang_tools/clang_format.py
cpp_linter/clang_tools/clang_tidy.py
cpp_linter/clang_tools/patcher.py
cpp_linter/common_fs/__init__.py
cpp_linter/common_fs/file_filter.py
cpp_linter/git/__init__.py
cpp_linter/git/git_str.py
cpp_linter/rest_api/__init__.py
cpp_linter/rest_api/github_api.py
cpp_linter-1.11.4.dist-info/licenses/LICENSE
cpp_linter-1.11.4.dist-info/METADATA
cpp_linter-1.11.4.dist-info/WHEEL
cpp_linter-1.11.4.dist-info/entry_points.txt
cpp_linter-1.11.4.dist-info/top_level.txt
cpp_linter-1.11.4.dist-info/RECORD
