Metadata-Version: 2.4
Name: cpp-linter
Version: 1.11.4
Summary: Run clang-format and clang-tidy on a batch of files.
Author-email: Brendan Doherty <2bndy5@gmail.com>, Xianpeng Shen <xianpeng.shen@gmail.com>
License-Expression: MIT
Project-URL: source, https://github.com/cpp-linter/cpp-linter
Project-URL: tracker, https://github.com/cpp-linter/cpp-linter/issues
Keywords: clang,clang-tools,linter,clang-tidy,clang-format
Classifier: Development Status :: 5 - Production/Stable
Classifier: Intended Audience :: Developers
Classifier: Intended Audience :: System Administrators
Classifier: Intended Audience :: Information Technology
Classifier: Natural Language :: English
Classifier: Operating System :: Microsoft :: Windows
Classifier: Operating System :: POSIX :: Linux
Classifier: Operating System :: MacOS
Classifier: Programming Language :: Python :: 3.9
Classifier: Programming Language :: Python :: 3.10
Classifier: Programming Language :: Python :: 3.11
Classifier: Programming Language :: Python :: 3.12
Classifier: Programming Language :: Python :: 3.13
Classifier: Programming Language :: Python :: 3.14
Classifier: Topic :: Software Development :: Build Tools
Requires-Python: >=3.9
License-File: LICENSE
Requires-Dist: pygit2>=1.15.1
Requires-Dist: pyyaml>=6.0.2
Requires-Dist: requests>=2.32.3
Dynamic: license-file
